README.rst
setup.py
pinguinoapi/__init__.py
pinguinoapi/base_api.py
pinguinoapi.egg-info/PKG-INFO
pinguinoapi.egg-info/SOURCES.txt
pinguinoapi.egg-info/dependency_links.txt
pinguinoapi.egg-info/requires.txt
pinguinoapi.egg-info/top_level.txt
test/__init__.py
test/test.py
test/pinguinoapi/__init__.py
test/pinguinoapi/base_api.py