Metadata-Version: 1.0
Name: pinguinoapi
Version: 0.1.2
Summary: Pinguino API module
Home-page: UNKNOWN
Author: Yeison Cardona
Author-email: yeisoneng@gmail.com
License: BSD 3-Clause
Keywords: pinguino
Platform: UNKNOWN
